audiogen_p3/__init__.py
audiogen_p3/filters.py
audiogen_p3/generators.py
audiogen_p3/noise.py
audiogen_p3/sampler.py
audiogen_p3/util.py
audiogen_p3-0.0.1.dist-info/LICENSE
audiogen_p3-0.0.1.dist-info/METADATA
audiogen_p3-0.0.1.dist-info/WHEEL
audiogen_p3-0.0.1.dist-info/top_level.txt
audiogen_p3-0.0.1.dist-info/RECORD
