Metadata-Version: 2.1
Name: audiogen-p3
Version: 0.0.1
Summary: Generator based tools for working with audio clips.
Home-page: https://github.com/rguisewite/audiogen_p3
Author: Ryan Guisewite
Author-email: ryan.guisewite@gmail.com
License: UNKNOWN
Platform: UNKNOWN
Classifier: License :: OSI Approved :: BSD License
Classifier: Programming Language :: Python :: 3.9
Classifier: Intended Audience :: Developers
Classifier: Topic :: Multimedia :: Sound/Audio
Requires-Python: >=3.6
Provides-Extra: soundcard_playback
Requires-Dist: pyaudio ; extra == 'soundcard_playback'
